ttskit/__init__.py
pyttskit-0.1.1.dist-info/LICENSE.md
pyttskit-0.1.1.dist-info/METADATA
pyttskit-0.1.1.dist-info/WHEEL
pyttskit-0.1.1.dist-info/top_level.txt
pyttskit-0.1.1.dist-info/RECORD
