Metadata-Version: 2.1
Name: pyttskit
Version: 0.1.1
Summary: Easily interact with many cutting-edge neural/AI text-to-speech models using one API, including transformer-powered text to speech and other advanced models!
Home-page: https://github.com/ospyp/TTSKit
Author: mrfakename
Author-email: me@mrfake.name
License: Multiple (See File). Main: NOSCL-C-2.0. Includes MIT, etc
License-File: LICENSE.md
